velib_data_analysis/__init__.py
velib_data_analysis/velib_monitoring.py
velib_monitoring-1.0.0.dist-info/LICENSE.md
velib_monitoring-1.0.0.dist-info/METADATA
velib_monitoring-1.0.0.dist-info/WHEEL
velib_monitoring-1.0.0.dist-info/entry_points.txt
velib_monitoring-1.0.0.dist-info/top_level.txt
velib_monitoring-1.0.0.dist-info/RECORD
