Metadata-Version: 2.1
Name: velib-monitoring
Version: 1.0.0
Summary: Un package pour l'analyse des données Vélib en temps réel.
Home-page: https://github.com/GhntSergio/velib-data-analysis
Author: Serge Ganhounouto
Author-email: serginhoganhounouto@gmail.com
Classifier: Programming Language :: Python :: 3
Classifier: License :: OSI Approved :: MIT License
Classifier: Operating System :: OS Independent
Requires-Python: >=3.6
License-File: LICENSE.md
Requires-Dist: requests
Requires-Dist: pandas
Requires-Dist: matplotlib
Requires-Dist: folium
Requires-Dist: jupyter
Requires-Dist: seaborn
